uniboost/__init__.py
uniboost/uniupdater.py
uniboost-0.8.38.dist-info/METADATA
uniboost-0.8.38.dist-info/WHEEL
uniboost-0.8.38.dist-info/top_level.txt
uniboost-0.8.38.dist-info/RECORD
