Metadata-Version: 2.1
Name: uniboost
Version: 0.8.38
Summary: AWS
Home-page: https://github.com/yourusername/your-package-name
Author: MIT
Author-email: UNKNOWN
License: UNKNOWN
Platform: UNKNOWN
